mkpipe_extractor_mariadb/__init__.py
mkpipe_extractor_mariadb/jars/com.github.ben-manes.caffeine_caffeine-2.9.3.jar
mkpipe_extractor_mariadb/jars/com.github.waffle_waffle-jna-3.3.0.jar
mkpipe_extractor_mariadb/jars/com.google.errorprone_error_prone_annotations-2.10.0.jar
mkpipe_extractor_mariadb/jars/net.java.dev.jna_jna-5.13.0.jar
mkpipe_extractor_mariadb/jars/net.java.dev.jna_jna-platform-5.13.0.jar
mkpipe_extractor_mariadb/jars/org.checkerframework_checker-qual-3.32.0.jar
mkpipe_extractor_mariadb/jars/org.mariadb.jdbc_mariadb-java-client-3.5.1.jar
mkpipe_extractor_mariadb/jars/org.slf4j_jcl-over-slf4j-2.0.7.jar
mkpipe_extractor_mariadb/jars/org.slf4j_slf4j-api-2.0.7.jar
mkpipe_extractor_mariadb-0.2.0.dist-info/licenses/LICENSE
mkpipe_extractor_mariadb-0.2.0.dist-info/METADATA
mkpipe_extractor_mariadb-0.2.0.dist-info/WHEEL
mkpipe_extractor_mariadb-0.2.0.dist-info/entry_points.txt
mkpipe_extractor_mariadb-0.2.0.dist-info/top_level.txt
mkpipe_extractor_mariadb-0.2.0.dist-info/RECORD
